odoo/addons/mass_operation_abstract/README.rst
odoo/addons/mass_operation_abstract/__init__.py
odoo/addons/mass_operation_abstract/__manifest__.py
odoo/addons/mass_operation_abstract/demo/res_groups.xml
odoo/addons/mass_operation_abstract/i18n/da.po
odoo/addons/mass_operation_abstract/i18n/es.po
odoo/addons/mass_operation_abstract/i18n/fr.po
odoo/addons/mass_operation_abstract/i18n/it.po
odoo/addons/mass_operation_abstract/i18n/mass_operation_abstract.pot
odoo/addons/mass_operation_abstract/i18n/pt.po
odoo/addons/mass_operation_abstract/models/__init__.py
odoo/addons/mass_operation_abstract/models/mass_operation_mixin.py
odoo/addons/mass_operation_abstract/readme/CONTRIBUTORS.rst
odoo/addons/mass_operation_abstract/readme/DESCRIPTION.rst
odoo/addons/mass_operation_abstract/readme/ROADMAP.rst
odoo/addons/mass_operation_abstract/static/description/icon.png
odoo/addons/mass_operation_abstract/static/description/index.html
odoo/addons/mass_operation_abstract/views/menu.xml
odoo/addons/mass_operation_abstract/views/view_mass_operation_mixin.xml
odoo/addons/mass_operation_abstract/views/view_mass_operation_wizard_mixin.xml
odoo/addons/mass_operation_abstract/wizard/__init__.py
odoo/addons/mass_operation_abstract/wizard/mass_operation_wizard_mixin.py
odoo12_addon_mass_operation_abstract-12.0.1.1.1.dist-info/METADATA
odoo12_addon_mass_operation_abstract-12.0.1.1.1.dist-info/WHEEL
odoo12_addon_mass_operation_abstract-12.0.1.1.1.dist-info/top_level.txt
odoo12_addon_mass_operation_abstract-12.0.1.1.1.dist-info/RECORD
